yengde/__init__.py
yengde/functions.py
yengde/greet.py
yengde/test.py
yengde-1.0.2.dist-info/LICENSE
yengde-1.0.2.dist-info/METADATA
yengde-1.0.2.dist-info/WHEEL
yengde-1.0.2.dist-info/entry_points.txt
yengde-1.0.2.dist-info/top_level.txt
yengde-1.0.2.dist-info/RECORD
