Metadata-Version: 2.1
Name: yengde
Version: 1.0.2
Summary: A Python package to get number table.
Home-page: UNKNOWN
Author: Shubham Yengde
Author-email: shubhamyengde@gmail.com
License: MIT
Platform: UNKNOWN
Classifier: License :: OSI Approved :: MIT License
Classifier: Programming Language :: Python :: 3
Classifier: Programming Language :: Python :: 3.8
